pitop/__init__.py
pitop/version.py
pitop/labs/README.md
pitop/labs/__init__.py
pitop/labs/web/__init__.py
pitop/labs/web/utils.py
pitop/labs/web/webcontroller.py
pitop/labs/web/webserver.py
pitop/labs/web/blueprints/__init__.py
pitop/labs/web/blueprints/base/__init__.py
pitop/labs/web/blueprints/base/base/index.css
pitop/labs/web/blueprints/base/templates/base.html
pitop/labs/web/blueprints/base/templates/index.html
pitop/labs/web/blueprints/controller/__init__.py
pitop/labs/web/blueprints/controller/templates/base-controller.html
pitop/labs/web/blueprints/controller/templates/index.html
pitop/labs/web/blueprints/messaging/__init__.py
pitop/labs/web/blueprints/messaging/messaging/pubsub.js
pitop/labs/web/blueprints/messaging/templates/setup-messaging.html
pitop/labs/web/blueprints/rover/__init__.py
pitop/labs/web/blueprints/rover/helpers.py
pitop/labs/web/blueprints/rover/templates/base-rover.html
pitop/labs/web/blueprints/rover/templates/index.html
pitop/labs/web/blueprints/video/__init__.py
pitop/labs/web/blueprints/video/templates/setup-video.html
pitop/labs/web/blueprints/video/video/styles.css
pitop/labs/web/blueprints/webcomponents/__init__.py
pitop/labs/web/blueprints/webcomponents/templates/setup-webcomponents.html
pitop/labs/web/blueprints/webcomponents/webcomponents/joystick-component.js
pitop/labs/web/blueprints/webcomponents/webcomponents/vendor/nipplejs.js
pitop/labs/web/blueprints/webcomponents/webcomponents/vendor/nipplejs.min.js
pitop/protoplus/__init__.py
pitop/protoplus/adc.py
pitop/protoplus/sensors.py
pitop/pulse/__init__.py
pitop/pulse/configuration.py
pitop/pulse/ledmatrix.py
pitop/pulse/microphone.py
pitop-0.34.3.post1.dist-info/METADATA
pitop-0.34.3.post1.dist-info/WHEEL
pitop-0.34.3.post1.dist-info/top_level.txt
pitop-0.34.3.post1.dist-info/RECORD
