Metadata-Version: 2.1
Name: pitop
Version: 0.34.3.post1
Summary: Pi-top Python SDK.
Home-page: https://github.com/pi-top/pi-top-Python-SDK
Author: pi-top
Author-email: deb-maintainers@pi-top.com
License: Apache Software License
Keywords: pi-top,raspberrypi,gpio
Platform: ALL
Classifier: Development Status :: 5 - Production/Stable
Classifier: Intended Audience :: Education
Classifier: Intended Audience :: Developers
Classifier: Topic :: Education
Classifier: Topic :: System :: Hardware
Classifier: License :: OSI Approved :: Apache Software License
Classifier: Programming Language :: Python :: 3
Classifier: Programming Language :: Python :: 3.7
Classifier: Programming Language :: Python :: 3.8
Classifier: Programming Language :: Python :: Implementation :: PyPy
Requires-Dist: pitop.battery ==0.34.3-1
Requires-Dist: pitop.camera ==0.34.3-1
Requires-Dist: pitop.common ==0.34.3-1
Requires-Dist: pitop.core ==0.34.3-1
Requires-Dist: pitop.display ==0.34.3-1
Requires-Dist: pitop.keyboard ==0.34.3-1
Requires-Dist: pitop.miniscreen ==0.34.3-1
Requires-Dist: pitop.pma ==0.34.3-1
Requires-Dist: pitop.processing ==0.34.3-1
Requires-Dist: pitop.robotics ==0.34.3-1
Requires-Dist: pitop.simulation ==0.34.3-1
Requires-Dist: pitop.system ==0.34.3-1
Requires-Dist: pitopcli ==0.34.3-1
Requires-Dist: gpiozero <2.0.0,>=1.6.2
Requires-Dist: pyserial <4.0,>=3.5
Requires-Dist: flask <3.0.0,>=1.1.2
Requires-Dist: flask-cors <4.0.0,>=3.0.9
Requires-Dist: gevent <23.0.0,>=20.9.0
Requires-Dist: gevent-websocket <1.0.0,>=0.10.1
Provides-Extra: computer_vision
Requires-Dist: opencv ; extra == 'computer_vision'
Provides-Extra: doc
Requires-Dist: sphinx ; extra == 'doc'
